YahooFinanceDataLoader/__init__.py
YahooFinanceDataLoader/asset_data/__init__.py
YahooFinanceDataLoader/asset_data/assetDataRequest.py
YahooFinanceDataLoader/asset_data/download_asset_data.py
YahooFinanceDataLoader/bulk_data/__init__.py
YahooFinanceDataLoader/bulk_data/download_bulk_data.py
YahooFinanceDataLoader/bulk_data/threadedLoader.py
YahooFinanceDataLoader/utils/__init__.py
YahooFinanceDataLoader/utils/get_assets_from_csv.py
YahooFinanceDataLoader/utils/set_time_point.py
tests/__init__.py
tests/asset_data/__init__.py
tests/asset_data/download_asset_data.py
tests/asset_data/assetsDataRequest/__init__.py
tests/asset_data/assetsDataRequest/init.py
tests/asset_data/assetsDataRequest/request_data_download.py
tests/asset_data/assetsDataRequest/request_download_permission.py
tests/utils/__init__.py
tests/utils/get_assets_from_csv.py
tests/utils/set_time_point_test.py
YahooFinanceDataLoader-0.1.0.dist-info/LICENSE
YahooFinanceDataLoader-0.1.0.dist-info/METADATA
YahooFinanceDataLoader-0.1.0.dist-info/WHEEL
YahooFinanceDataLoader-0.1.0.dist-info/top_level.txt
YahooFinanceDataLoader-0.1.0.dist-info/RECORD
