Metadata-Version: 2.1
Name: YahooFinanceDataLoader
Version: 0.1.0
Summary: Allows to download YahooFinance stock data to your local disk.
Home-page: https://github.com/alv2017/Python---YahooFinanceDataLoader
Author: Maverick
Author-email: maverickjet@protonmail.com
License: UNKNOWN
Keywords: Yahoo Finance stock price csv
Platform: UNKNOWN
Classifier: Programming Language :: Python :: 3
Classifier: License :: OSI Approved :: MIT License
Classifier: Operating System :: POSIX :: Linux
Requires-Python: ~=3.6
Requires-Dist: requests (~=2.20.00)
